lbsntransform/__init__.py
lbsntransform/__main__.py
lbsntransform/lbsntransform_.py
lbsntransform/version.py
lbsntransform/config/__init__.py
lbsntransform/config/config.py
lbsntransform/input/__init__.py
lbsntransform/input/load_data.py
lbsntransform/input/mappings/__init__.py
lbsntransform/input/mappings/db_query.py
lbsntransform/input/mappings/field_mapping_lbsn.py
lbsntransform/output/__init__.py
lbsntransform/output/shared_structure.py
lbsntransform/output/submit_data.py
lbsntransform/output/csv/__init__.py
lbsntransform/output/csv/store_csv.py
lbsntransform/output/hll/__init__.py
lbsntransform/output/hll/hll_bases.py
lbsntransform/output/hll/hll_functions.py
lbsntransform/output/hll/shared_structure_proto_hlldb.py
lbsntransform/output/hll/sql_hll.py
lbsntransform/output/hll/base/__init__.py
lbsntransform/output/hll/base/social.py
lbsntransform/output/hll/base/spatial.py
lbsntransform/output/hll/base/temporal.py
lbsntransform/output/hll/base/topical.py
lbsntransform/output/lbsn/__init__.py
lbsntransform/output/lbsn/shared_structure_proto_lbsndb.py
lbsntransform/output/lbsn/sql_lbsn.py
lbsntransform/tools/__init__.py
lbsntransform/tools/db_connection.py
lbsntransform/tools/helper_functions.py
lbsntransform-0.26.0.dist-info/LICENSE.md
lbsntransform-0.26.0.dist-info/METADATA
lbsntransform-0.26.0.dist-info/WHEEL
lbsntransform-0.26.0.dist-info/entry_points.txt
lbsntransform-0.26.0.dist-info/top_level.txt
lbsntransform-0.26.0.dist-info/RECORD
