Metadata-Version: 2.1
Name: lbsntransform
Version: 0.26.0
Summary: Location based social network (LBSN) data structure format & transfer tool
Author-email: Alexander Dunkel <alexander.dunkel@tu-dresden.de>
License: GNU GPLv3 or any higher
Project-URL: Homepage, https://gitlab.vgiscience.de/lbsn/lbsntransform
Requires-Python: >=3.8
License-File: LICENSE.md
Requires-Dist: lbsnstructure (>=1.2.0)
Requires-Dist: protobuf (<5,>=4.21.9)
Requires-Dist: psycopg2-binary
Requires-Dist: ppygis3
Requires-Dist: shapely (<2.0.0)
Requires-Dist: emoji (>=2.0.0)
Requires-Dist: requests
Requires-Dist: geos
Requires-Dist: numpy
Requires-Dist: regex
Provides-Extra: nltk_stopwords
Requires-Dist: nltk ; extra == 'nltk_stopwords'
